coltra/__init__.py
coltra/agents.py
coltra/buffers.py
coltra/collectors.py
coltra/configs.py
coltra/data_utils.py
coltra/discounting.py
coltra/groups.py
coltra/policy_optimization.py
coltra/schedule.py
coltra/trainers.py
coltra/training_utils.py
coltra/unity_utils.py
coltra/utils.py
coltra/envs/__init__.py
coltra/envs/base_env.py
coltra/envs/decision_envs.py
coltra/envs/energy_env.py
coltra/envs/gym_envs.py
coltra/envs/navigation_env.py
coltra/envs/normalization.py
coltra/envs/pettingzoo_envs.py
coltra/envs/probe_envs.py
coltra/envs/side_channels.py
coltra/envs/spaces.py
coltra/envs/subproc_vec_env.py
coltra/envs/unity_envs.py
coltra/envs/vec_env.py
coltra/models/__init__.py
coltra/models/attention_models.py
coltra/models/base_models.py
coltra/models/lstm_models.py
coltra/models/mlp_models.py
coltra/models/model_utils.py
coltra/models/relational_models.py
coltra/research/__init__.py
coltra/research/policy_fusion/__init__.py
coltra/research/policy_fusion/fusion_trainer.py
coltra/research/policy_fusion/policy_fusion.py
coltra/research/policy_fusion/schedules.py
coltra/wrappers/__init__.py
coltra/wrappers/agent_wrappers.py
coltra/wrappers/base_wrappers.py
coltra/wrappers/env_wrappers.py
coltra-0.2.1.dist-info/METADATA
coltra-0.2.1.dist-info/WHEEL
coltra-0.2.1.dist-info/RECORD
