Metadata-Version: 2.1
Name: coltra
Version: 0.2.1
Summary: Coltra is a simple moddable RL algorithm implementation
Project-URL: Homepage, https://github.com/redtachyon/coltra-rl
Author-email: Ariel Kwiatkowski <ariel.j.kwiatkowski@gmail.com>
License-Expression: MIT
Requires-Dist: cloudpickle~=2.2.1
Requires-Dist: gymnasium~=0.29.1
Requires-Dist: numba>=0.56.4
Requires-Dist: numpy==1.23.5
Requires-Dist: optuna~=3.1.0
Requires-Dist: pettingzoo>=1.22.3
Requires-Dist: pillow~=9.4.0
Requires-Dist: pyyaml>=6.0
Requires-Dist: setuptools~=65.6.3
Requires-Dist: shortuuid==1.0.11
Requires-Dist: supersuit>=3.7.1
Requires-Dist: torch>=1.13.1
Requires-Dist: tqdm>=4.64.1
Requires-Dist: typarse==3.4.0
Provides-Extra: dev
Requires-Dist: black==22.3.0; extra == 'dev'
Requires-Dist: coverage>=7.1.0; extra == 'dev'
Requires-Dist: jupyter>=1.0.0; extra == 'dev'
Requires-Dist: jupyterlab>=3.5.3; extra == 'dev'
Requires-Dist: pytest>=7.2.1; extra == 'dev'
Requires-Dist: pytype==2023.1.17; extra == 'dev'
Requires-Dist: pyvirtualdisplay~=3.0; extra == 'dev'
Provides-Extra: experiments
Requires-Dist: tensorboard>=2.11.2; extra == 'experiments'
Requires-Dist: wandb>=0.13.9; extra == 'experiments'
Provides-Extra: extra
Requires-Dist: jax==0.4.1; extra == 'extra'
Requires-Dist: jaxlib==0.4.1; extra == 'extra'
Requires-Dist: pybullet==3.2.5; extra == 'extra'
Provides-Extra: unity
Requires-Dist: mlagents-envs~=0.28.0; extra == 'unity'
Provides-Extra: visualization
Requires-Dist: ipykernel>=6.20.2; extra == 'visualization'
Requires-Dist: matplotlib==3.6.3; extra == 'visualization'
Requires-Dist: seaborn>=0.12.2; extra == 'visualization'
